LICENSE.txt
MANIFEST.in
README.md
setup.py
starksign/__init__.py
starksign.egg-info/PKG-INFO
starksign.egg-info/SOURCES.txt
starksign.egg-info/dependency_links.txt
starksign.egg-info/requires.txt
starksign.egg-info/top_level.txt
starksign/document/__document.py
starksign/document/__init__.py
starksign/document/signature/__init__.py
starksign/document/signature/__signature.py
starksign/document/signer/__init__.py
starksign/document/signer/__signer.py
starksign/signaturerequest/__init__.py
starksign/signaturerequest/__signaturerequest.py
starksign/utils/__init__.py
starksign/utils/parse.py
starksign/utils/relay.py
starksign/utils/rest.py