Metadata-Version: 2.1
Name: starksign
Version: 0.0.1
Summary: SDK to facilitate Python integrations with Stark Sign
Home-page: https://github.com/starksign/sdk-python
Author: Stark Sign
Author-email: developers@starkinfra.com
License: MIT License
Keywords: stark sign,starksign,sdk,stark
Platform: UNKNOWN
